witcher/FileChooser.py
witcher/ImageToCartoon.py
witcher/Portfolio_Advisor.py
witcher/Recommender.py
witcher/StockMarket.py
witcher/__init__.py
witcher/util/Witcher_MC_0.3.pkl
witcher/util/Witcher_MC_1.0.pkl
witcher-0.0.41.dist-info/METADATA
witcher-0.0.41.dist-info/WHEEL
witcher-0.0.41.dist-info/license
witcher-0.0.41.dist-info/top_level.txt
witcher-0.0.41.dist-info/RECORD
