Metadata-Version: 2.1
Name: witcher
Version: 0.0.41
Summary: Automated AI tool including: recommender system, deep Learnings ...
Home-page: https://github.com/BabakEA/witcher
Author: Babak EA, Founder and CEO: AI Forest Inc 
Author-email: emami.babak@gmail.com
License-File: license
Requires-Dist: stdlib-list
Requires-Dist: ipywidgets
Requires-Dist: pandas
Requires-Dist: sklearn
Requires-Dist: traitlets
Requires-Dist: IPython
Requires-Dist: statsmodels
Requires-Dist: seaborn
Requires-Dist: matplotlib
Requires-Dist: yfinance
Requires-Dist: pmdarima
Requires-Dist: plotly
Requires-Dist: opencv-python
Provides-Extra: test
Requires-Dist: IPython ; extra == 'test'
Requires-Dist: notebook ; extra == 'test'
